LICENSE
MANIFEST.in
README.md
README.rst
setup.py
lagmat/__init__.py
lagmat/lagmat.py
lagmat/utils.py
lagmat.egg-info/PKG-INFO
lagmat.egg-info/SOURCES.txt
lagmat.egg-info/dependency_links.txt
lagmat.egg-info/requires.txt
lagmat.egg-info/top_level.txt
lagmat.egg-info/zip-safe
test/__init__.py
test/test_lagmat.py